pandora_llm/__init__.py
pandora_llm/attacks/ALoRa.py
pandora_llm/attacks/Attack.py
pandora_llm/attacks/DetectGPT.py
pandora_llm/attacks/FLoRa.py
pandora_llm/attacks/GradNorm.py
pandora_llm/attacks/JL.py
pandora_llm/attacks/LOSS.py
pandora_llm/attacks/LogReg.py
pandora_llm/attacks/MinK.py
pandora_llm/attacks/MoPe.py
pandora_llm/attacks/ModelStealing.py
pandora_llm/attacks/NN.py
pandora_llm/attacks/ZLIB.py
pandora_llm/attacks/ZLIBLoRa.py
pandora_llm/attacks/__init__.py
pandora_llm/routines/__init__.py
pandora_llm/routines/model_embedding.py
pandora_llm/routines/model_generation.py
pandora_llm/routines/model_inference.py
pandora_llm/routines/model_train.py
pandora_llm/utils/__init__.py
pandora_llm/utils/dataset_utils.py
pandora_llm/utils/extraction_utils.py
pandora_llm/utils/generation_utils.py
pandora_llm/utils/log_utils.py
pandora_llm/utils/plot_utils.py
pandora_llm-2024.6.25.dist-info/LICENSE.txt
pandora_llm-2024.6.25.dist-info/METADATA
pandora_llm-2024.6.25.dist-info/WHEEL
pandora_llm-2024.6.25.dist-info/top_level.txt
pandora_llm-2024.6.25.dist-info/RECORD
