Metadata-Version: 2.1
Name: pandora_llm
Version: 2024.6.25
Summary: Red-teaming large language models for train data leakage
Author: Jeffrey Wang, Jason Wang, Marvin Li, Seth Neel
License: MIT License
Project-URL: Homepage, https://safr-ai.quarto.pub/pandora/
Project-URL: Documentation, https://pandora-llm.readthedocs.io/en/latest/
Project-URL: Repository, https://github.com/safr-ai-lab/pandora-llm
Keywords: red-teaming,privacy,large language model,membership inference attack,extraction
Classifier: Programming Language :: Python
Requires-Python: >=3.10
License-File: LICENSE.txt
Requires-Dist: python ==3.10
Requires-Dist: torch ==2.3.0
Requires-Dist: torchvision ==0.18.0
Requires-Dist: torchaudio ==2.3.0
Requires-Dist: transformers ==4.41.0
Requires-Dist: datasets ==2.19.1
Requires-Dist: zstandard ==0.22.0
Requires-Dist: deepspeed ==0.14.2
Requires-Dist: accelerate ==0.30.1
Requires-Dist: scikit-learn ==1.5.0
Requires-Dist: matplotlib ==3.9.0
Requires-Dist: plotly ==5.22.0
Requires-Dist: kaleido ==0.1.0
Requires-Dist: sentencepiece ==0.2.0
Requires-Dist: setuptools ==70.0.0
Requires-Dist: einops ==0.7.0
Requires-Dist: traker ==0.3.2
